pyPRISMClimate/__init__.py
pyPRISMClimate/base.py
pyPRISMClimate/quick_tools.py
pyPRISMClimate/utils.py
pyPRISMClimate/version.py
pyPRISMClimate-0.2.3.dist-info/LICENSE
pyPRISMClimate-0.2.3.dist-info/METADATA
pyPRISMClimate-0.2.3.dist-info/WHEEL
pyPRISMClimate-0.2.3.dist-info/top_level.txt
pyPRISMClimate-0.2.3.dist-info/RECORD
