Metadata-Version: 2.1
Name: pyPRISMClimate
Version: 0.2.3
Summary: An interface to the PRISM Climate data
Home-page: https://github.com/sdtaylor/pyPRISMClimate
Author: Shawn Taylor
License: MIT
Platform: UNKNOWN
Requires-Python: >=3.6.0
License-File: LICENSE
